jenkins_log_scanner/__init__.py
jenkins_log_scanner/__main__.py
jenkins_log_scanner/log_operations.py
jenkins_log_scanner/scan_jenkins.py
jenkins_log_scanner/string_utils.py
jenkins_log_scanner-0.0.4.dist-info/LICENSE
jenkins_log_scanner-0.0.4.dist-info/METADATA
jenkins_log_scanner-0.0.4.dist-info/WHEEL
jenkins_log_scanner-0.0.4.dist-info/top_level.txt
jenkins_log_scanner-0.0.4.dist-info/RECORD
