Metadata-Version: 2.2
Name: jenkins_log_scanner
Version: 0.0.4
Summary: A package for efficiently scanning logs in Jenkins projects
Author-email: Adeiron Barolli <obarolli@onicodes.io>
License: Copyright (c) 2025 The Python Packaging Authority
Project-URL: Homepage, https://github.com/abarolli/JenkinsLogScanner
Project-URL: Issues, https://github.com/abarolli/JenkinsLogScanner/issues
Classifier: Programming Language :: Python :: 3
Classifier: Operating System :: OS Independent
Requires-Python: >=3.8
License-File: LICENSE
Requires-Dist: requests
Requires-Dist: validators
